bsavi/__init__.py
bsavi/bsavi.py
bsavi/cosmo/__init__.py
bsavi/cosmo/cosmo.py
bsavi/loaders/__init__.py
bsavi/loaders/loaders.py
bsavi-0.4.0.dist-info/LICENSE
bsavi-0.4.0.dist-info/METADATA
bsavi-0.4.0.dist-info/WHEEL
bsavi-0.4.0.dist-info/top_level.txt
bsavi-0.4.0.dist-info/RECORD
