Metadata-Version: 2.1
Name: bsavi
Version: 0.4.0
Summary: An interactive visualizer to help explore high-dimensional likelihoods and their observables.
Home-page: http://packages.python.org/bsavi
Author: James Wen
Author-email: jswen@usc.edu
License: MIT
Keywords: interactive visualizer cosmology
Classifier: Programming Language :: Python :: 3
Classifier: License :: OSI Approved :: MIT License
Classifier: Operating System :: POSIX :: Linux
Requires-Python: >=3.8, <3.12
License-File: LICENSE
Requires-Dist: holoviews >=1.15.4
Requires-Dist: bokeh ==2.4.3
Requires-Dist: panel ==0.14.4
Requires-Dist: spatialpandas ==0.4.8
Requires-Dist: dask <=2023.5.0
Requires-Dist: param ==1.13.0
Requires-Dist: numpy <=1.24,>=1.21
Requires-Dist: matplotlib ==3.7.1
